blink_celery/__init__.py
blink_celery-0.1.1.dist-info/LICENSE
blink_celery-0.1.1.dist-info/METADATA
blink_celery-0.1.1.dist-info/WHEEL
blink_celery-0.1.1.dist-info/top_level.txt
blink_celery-0.1.1.dist-info/RECORD
