Metadata-Version: 2.1
Name: blink-celery
Version: 0.1.1
Summary: Library to create/execute celery tasks for blink cameras
Home-page: UNKNOWN
Author: Daniel Munoz
Author-email: dmunozg@gmail.com
License: UNKNOWN
Platform: UNKNOWN
Classifier: Programming Language :: Python :: 3
Classifier: License :: OSI Approved :: BSD License
Classifier: Operating System :: OS Independent
Requires-Dist: blink-cameras
Requires-Dist: celery
